antifragility_schema/__init__.py
antifragility_schema/models.py
antifragility_schema-0.3.7.dist-info/METADATA
antifragility_schema-0.3.7.dist-info/WHEEL
antifragility_schema-0.3.7.dist-info/top_level.txt
antifragility_schema-0.3.7.dist-info/RECORD
